VITimeCLI/Slotdata.py
VITimeCLI/__init__.py
VITimeCLI/functions.py
VITimeCLI/initialize.py
VITimeCLI/main.py
vitime-0.2.2.dist-info/LICENSE
vitime-0.2.2.dist-info/METADATA
vitime-0.2.2.dist-info/WHEEL
vitime-0.2.2.dist-info/entry_points.txt
vitime-0.2.2.dist-info/top_level.txt
vitime-0.2.2.dist-info/RECORD
